dbexport/__init__.py
dbexport/csv_export.py
dbexport/json_export.py
dbexport/configdb/__init__.py
dbexport/configdb/config_db.py
dbexport/models/__init__.py
dbexport/models/models.py
dbexport-0.1.0.dist-info/LICENSE
dbexport-0.1.0.dist-info/METADATA
dbexport-0.1.0.dist-info/WHEEL
dbexport-0.1.0.dist-info/entry_points.txt
dbexport-0.1.0.dist-info/top_level.txt
dbexport-0.1.0.dist-info/RECORD
